{

	"post":{
		"domingo" : ["10h", "14h"],
		"segunda" : ["11h", "17h"],
		"terça" :["5h" , "9h-18h"],
		"quarta":["5h", "11h-15h"],
		"quinta":["5h", "11h-15h"],
		"sexta":["5h", "9h-16h"],
		"sábado":["11h", "nulo"]
	},
	
	"story":{
		"domingo" : ["10h", "14h"],
		"segunda" : ["11h", "17h"],
		"terça" :["5h" , "9h-18h"],
		"quarta":["5h", "11h-15h"],
		"quinta":["5h", "11h-15h"],
		"sexta":["5h", "9h-16h"],
		"sábado":["11h", "nulo"]
	},
	
	"reels":{
		"domingo" : ["10h", "14h"],
		"segunda" : ["11h", "17h"],
		"terça" :["5h" , "9h-18h"],
		"quarta":["5h", "11h-15h"],
		"quinta":["5h", "11h-15h"],
		"sexta":["5h", "9h-16h"],
		"sábado":["11h", "nulo"]
	}
	
}
